EL3011_2_20251119_13223048/1_lab/Tugas1/ctrl_unit_rv32i.v
// Praktikum EL3011 Arsitektur Sistem Komputer
// Modul      : 2
// Percobaan  : 1
// Tanggal    : 19 November 2025
// Nama (NIM) 1 : William Anthony (13223048)
// Nama (NIM) 2 : Agita Trinanda Ilmi (13223003)
// Nama File    : ctrl_unit_rv32i.v
// Deskripsi    : Control Unit (CU) untuk Percobaan 1 RV32I
//                [Register terletak pada cite: 141]

module ctrl_unit_rv32i (
    input wire [6:0] opcode,
    input wire [2:0] funct3,
    input wire [6:0] funct7,
    
    output reg cu_ALU1src,
    output reg cu_ALU2src,
    output reg [2:0] cu_immtype,
    output reg [1:0] cu_ALUtype,
    output reg cu_adtype,
    output reg [1:0] cu_gatype,
    output reg [1:0] cu_shiftype,
    output reg cu_sltype,
    output reg [1:0] cu_rdtype,
    output reg cu_rdwrite,
    output reg [2:0] cu_loadtype,
    output reg cu_store,
    output reg [1:0] cu_storetype,
    output reg cu_branch,
    output reg [2:0] cu_branchtype,
    output reg cu_PCtype
);

always @ (*) 
begin
    // [Register di cite: 146-187]
    cu_ALU1src    = 1'b0; // Dari rs1
    cu_ALU2src    = 1'b0; // Dari rs2
    cu_immtype    = 3'b000; // I-type
    cu_ALUtype    = 2'b00; // ADD/SUB
    cu_adtype     = 1'b0; // Addition
    cu_gatype     = 2'b00; // AND
    cu_shiftype   = 2'b00; // SLL
    cu_sltype     = 1'b0; // SLT (Signed)
    cu_rdtype     = 2'b00; // Dari ALU
    cu_rdwrite    = 1'b0; // No Write
    cu_loadtype   = 3'b010; // Load Word (LW) by default
    cu_store      = 1'b0; // No Store
    cu_storetype  = 2'b00; // Store Byte (SB) by default
    cu_branch     = 1'b0; // No Branch
    cu_branchtype = 3'b000; // BEQ
    cu_PCtype     = 1'b0; // PC + 4

    // --- Main Logic Decoder dengan Source Opcode ---
    case (opcode) 
    
        // R-type [Register di cite: 182]
        7'h33:
        begin
            cu_rdwrite = 1'b1; 
            case (funct3) 
                // ADD/SUB [Register di cite: 190]
                3'h0: 
                begin
                    if (funct7 == 7'h20) // SUB [Register di cite: 192]
                        cu_adtype = 1'b1;
                end
                // SLL [Register di cite: 193]
                3'h1: 
                begin
                    cu_ALUtype = 2'b10; // Shift op [Register di cite: 194]
                end
                // SLT [Register di cite: 196]
                3'h2:
                begin
                    cu_ALUtype = 2'b11; // SLT op [Register di cite: 197]
                end
                // SLTU [Register di cite: 199]
                3'h3:
                begin
                    cu_ALUtype = 2'b11; // SLT op [Register di cite: 201]
                    cu_sltype = 1'b1;  // Unsigned [Register di cite: 203]
                end
                // XOR [Register di cite: 205]
                3'h4:
                begin
                    cu_ALUtype = 2'b01; // Gate op [Register di cite: 207]
                    cu_gatype = 2'b10; // XOR (template salah, 2'b11 itu tidak ada) [Register di cite: 209, 30]
                end
                // SRL/SRA [Register di cite: 211]
                3'h5:
                begin
                    cu_ALUtype = 2'b10; // Shift op [Register di cite: 213]
                    if (funct7 == 7'h00)
                        cu_shiftype = 2'b01; // SRL [Register di cite: 214, 216]
                    else
                        cu_shiftype = 2'b11; // SRA [Register di cite: 217, 218]
                end
                // OR [Register di cite: 221]
                3'h6:
                begin
                    cu_ALUtype = 2'b01; // Gate op [Register di cite: 224]
                    cu_gatype = 2'b01; // OR [Register di cite: 224]
                end
                // AND [Register di cite: 225]
                3'h7:
                begin
                    cu_ALUtype = 2'b01; // Gate op [Register di cite: 227]
                    // cu_gatype = 2'b00 nilainya pasti default
                end
            endcase
        end
        
        // I-type (ALU) [Register di cite: 228]
        7'h13:
        begin
            cu_ALU2src = 1'b1; // Dari immediate
            cu_rdwrite = 1'b1; // Tulis ke rd
            // cu_immtype = 3'b000 (I-type) bernilai pasti default
            
            case (funct3)
                // ADDI (default, tidak perlu di-case)
                // 3'h0: 
                
                // SLLI [Register di cite: 232]
                3'h1:
                begin
                    cu_ALUtype = 2'b10; // Shift op
                    // cu_shiftype = 2'b00 (SLL) bernilai pasti default
                end
                // SLTI [Register di cite: 234]
                3'h2:
                begin
                    cu_ALUtype = 2'b11; // SLT op
                    // cu_sltype = 1'b0 (Signed) sudah default
                end
                // SLTIU
                3'h3:
                begin
                    cu_ALUtype = 2'b11; // SLT op
                    cu_sltype = 1'b1;  // Unsigned
                end
                // XORI
                3'h4:
                begin
                    cu_ALUtype = 2'b01; // Gate op
                    cu_gatype = 2'b10; // XOR
                end
                // SRLI/SRAI
                3'h5:
                begin
                    cu_ALUtype = 2'b10; // Shift op
                    if (funct7 == 7'h00)
                        cu_shiftype = 2'b01; // SRLI
                    else
                        cu_shiftype = 2'b11; // SRAI
                end
                // ORI
                3'h6:
                begin
                    cu_ALUtype = 2'b01; // Gate op
                    cu_gatype = 2'b01; // OR
                end
                // ANDI
                3'h7:
                begin
                    cu_ALUtype = 2'b01; // Gate op
                    // cu_gatype = 2'b00 (AND) bernilai pasti default
                end
            endcase
        end

        // Load (I-type) [Register di cite: 240]
        7'h03:
        begin
            cu_ALU2src = 1'b1; // Dari immediate
            // cu_immtype = 3'b000 (I-type) bernilai pasti default
            cu_rdtype = 2'b01; // Dari memori
            cu_rdwrite = 1'b1; // Tulis ke rd
            
            case (funct3)
                3'h0: cu_loadtype = 3'b000; // LB
                3'h1: cu_loadtype = 3'b001; // LH
                3'h2: cu_loadtype = 3'b010; // LW
                3'h3: cu_loadtype = 3'b011; // LBU
                3'h4: cu_loadtype = 3'b100; // LHU
            endcase
        end

        // S-type (Store) [Register di cite: 243]
        7'h23:
        begin
            cu_ALU2src = 1'b1; // Dari immediate
            cu_immtype = 3'b001; // S-type
            cu_store = 1'b1;   // Aktifkan store
            
            case (funct3)
                3'h0: cu_storetype = 2'b00; // SB
                3'h1: cu_storetype = 2'b01; // SH
                3'h2: cu_storetype = 2'b10; // SW
            endcase
        end

        // B-type (Branch) [Register di cite: 247]
        7'h63:
        begin
            cu_ALU1src = 1'b1; // Dari PC
            cu_ALU2src = 1'b1; // Dari immediate
            cu_immtype = 3'b010; // B-type
            cu_branch = 1'b1;   // Aktifkan branch
            cu_PCtype = 1'b1;   // Ambil PC dari ALU (target branch)
            
            case (funct3)
                3'h0: cu_branchtype = 3'b000; // BEQ
                3'h1: cu_branchtype = 3'b101; // BNE
                3'h4: cu_branchtype = 3'b011; // BLT
                3'h5: cu_branchtype = 3'b001; // BGE
                3'h6: cu_branchtype = 3'b100; // BLTU
                3'h7: cu_branchtype = 3'b010; // BGEU
            endcase
        end
        
        // LUI (U-type) [Register di cite: 251]
        7'h37:
        begin
            cu_ALU2src = 1'b1; // Dari immediate
            cu_immtype = 3'b011; // U-type
            cu_rdtype = 2'b11; // Dari immediate (ke rd)
            cu_rdwrite = 1'b1; // Tulis ke rd
        end

        // AUIPC (U-type) [Register di cite: 255]
        7'h17:
        begin
            cu_ALU1src = 1'b1; // Dari PC
            cu_ALU2src = 1'b1; // Dari immediate
            cu_immtype = 3'b011; // U-type
            cu_rdwrite = 1'b1; // Tulis ke rd
            // cu_rdtype = 2'b00 (Dari ALU) bernilai pasti default
        end

        // JAL (J-type) [Register di cite: 259]
        7'h6F:
        begin
            cu_ALU1src = 1'b1; // Dari PC
            cu_ALU2src = 1'b1; // Dari immediate
            cu_immtype = 3'b100; // J-type
            cu_rdtype = 2'b10; // Dari PC+4
            cu_rdwrite = 1'b1; // Tulis ke rd
            cu_branch = 1'b1;   // Aktifkan jump
            cu_PCtype = 1'b1;   // Ambil PC dari ALU (target jump)
        end
        
        // JALR (I-type) [Register di cite: 263]
        7'h67:
        begin
            // cu_ALU1src = 1'b0 (Dari rs1) bernilai pasti default
            cu_ALU2src = 1'b1; // Dari immediate
            // cu_immtype = 3'b000 (I-type) bernilai pasti default
            cu_rdtype = 2'b10; // Dari PC+4
            cu_rdwrite = 1'b1; // Tulis ke rd
            cu_branch = 1'b1;   // Aktifkan jump
            cu_PCtype = 1'b1;   // Ambil PC dari ALU (target jump)
        end

    endcase
end

endmodule

EL3011_2_20251119_13223048/1_lab/Tugas 1/tb_ctrl_unit_rv32i.v
// Praktikum EL3011 Arsitektur Sistem Komputer
// Modul      : 2
// Percobaan  : 1
// Tanggal    : 19 November 2025
// Nama (NIM) 1 : William Anthony (13223048)
// Nama (NIM) 2 : Agita Trinanda Ilmi (13223003)
// Nama File  : tb_ctrl_unit_rv32i.v
// Deskripsi  : Testbench untuk Control Unit (CU) RV32I

`timescale 1ns / 1ps

module tb_ctrl_unit_rv32i;

    // Deklarasi sinyal testbench untuk input CU
    reg [6:0] opcode_tb;
    reg [2:0] funct3_tb;
    reg [6:0] funct7_tb;

    // Deklarasi sinyal testbench untuk output CU
    wire       cu_ALU1src_tb;
    wire       cu_ALU2src_tb;
    wire [2:0] cu_immtype_tb;
    wire [1:0] cu_ALUtype_tb;
    wire       cu_adtype_tb;
    wire [1:0] cu_gatype_tb;
    wire [1:0] cu_shiftype_tb;
    wire       cu_sltype_tb;
    wire [1:0] cu_rdtype_tb;
    wire       cu_rdwrite_tb;
    wire [2:0] cu_loadtype_tb;
    wire       cu_store_tb;
    wire [1:0] cu_storetype_tb;
    wire       cu_branch_tb;
    wire [2:0] cu_branchtype_tb;
    wire       cu_PCtype_tb;

    // Instansiasi Unit Under Test (UUT)
    // Diasumsikan ctrl_unit_rv32i.v ada di direktori yang sama
    ctrl_unit_rv32i uut (
        .opcode(opcode_tb),
        .funct3(funct3_tb),
        .funct7(funct7_tb),

        .cu_ALU1src(cu_ALU1src_tb),
        .cu_ALU2src(cu_ALU2src_tb),
        .cu_immtype(cu_immtype_tb),
        .cu_ALUtype(cu_ALUtype_tb),
        .cu_adtype(cu_adtype_tb),
        .cu_gatype(cu_gatype_tb),
        .cu_shiftype(cu_shiftype_tb),
        .cu_sltype(cu_sltype_tb),
        .cu_rdtype(cu_rdtype_tb),
        .cu_rdwrite(cu_rdwrite_tb),
        .cu_loadtype(cu_loadtype_tb),
        .cu_store(cu_store_tb),
        .cu_storetype(cu_storetype_tb),
        .cu_branch(cu_branch_tb),
        .cu_branchtype(cu_branchtype_tb),
        .cu_PCtype(cu_PCtype_tb)
    );

    initial begin
        // Konfigurasi pencatatan waveform
        $dumpfile("cu_sim.vcd");
        $dumpvars(0, tb_ctrl_unit_rv32i);

        // Inisialisasi awal
        opcode_tb = 7'b0; funct3_tb = 3'b0; funct7_tb = 7'b0; #10;

        // --- Kasus Uji R-type (opcode = 7'h33) ---
        $display("\n--- Uji R-type ---");
        // ADD (funct3=0, funct7=0)
        opcode_tb = 7'h33; funct3_tb = 3'h0; funct7_tb = 7'h00; #10;
        // Output diharapkan: cu_rdwrite=1, cu_ALUtype=00, cu_adtype=0, sisanya default/don't care

        // SUB (funct3=0, funct7=0x20)
        funct7_tb = 7'h20; #10;
        // Output diharapkan: cu_rdwrite=1, cu_ALUtype=00, cu_adtype=1

        // SLL (funct3=1, funct7=0)
        funct3_tb = 3'h1; funct7_tb = 7'h00; #10;
        // Output diharapkan: cu_rdwrite=1, cu_ALUtype=10

        // SLTU (funct3=3, funct7=0)
        funct3_tb = 3'h3; funct7_tb = 7'h00; #10;
        // Output diharapkan: cu_rdwrite=1, cu_ALUtype=11, cu_sltype=1

        // XOR (funct3=4, funct7=0)
        funct3_tb = 3'h4; funct7_tb = 7'h00; #10;
        // Output diharapkan: cu_rdwrite=1, cu_ALUtype=01, cu_gatype=10

        // SRL (funct3=5, funct7=0)
        funct3_tb = 3'h5; funct7_tb = 7'h00; #10;
        // Output diharapkan: cu_rdwrite=1, cu_ALUtype=10, cu_shiftype=01

        // SRA (funct3=5, funct7=0x20)
        funct7_tb = 7'h20; #10;
        // Output diharapkan: cu_rdwrite=1, cu_ALUtype=10, cu_shiftype=11

        // --- Kasus Uji I-type (ALU) (opcode = 7'h13) ---
        $display("\n--- Uji I-type (ALU) ---");
        // ADDI (funct3=0, funct7=0)
        opcode_tb = 7'h13; funct3_tb = 3'h0; funct7_tb = 7'h00; #10;
        // Output diharapkan: cu_ALU2src=1, cu_rdwrite=1, cu_immtype=000, cu_ALUtype=00, cu_adtype=0

        // XORI (funct3=4, funct7=0)
        funct3_tb = 3'h4; funct7_tb = 7'h00; #10;
        // Output diharapkan: cu_ALU2src=1, cu_rdwrite=1, cu_immtype=000, cu_ALUtype=01, cu_gatype=10

        // --- Kasus Uji Load (I-type, opcode = 7'h03) ---
        $display("\n--- Uji Load ---");
        // LW (funct3=2)
        opcode_tb = 7'h03; funct3_tb = 3'h2; #10;
        // Output diharapkan: cu_ALU2src=1, cu_immtype=000, cu_rdtype=01, cu_rdwrite=1, cu_loadtype=010

        // LBU (funct3=3)
        funct3_tb = 3'h3; #10;
        // Output diharapkan: cu_ALU2src=1, cu_immtype=000, cu_rdtype=01, cu_rdwrite=1, cu_loadtype=011

        // --- Kasus Uji S-type (Store) (opcode = 7'h23) ---
        $display("\n--- Uji Store ---");
        // SW (funct3=2)
        opcode_tb = 7'h23; funct3_tb = 3'h2; #10;
        // Output diharapkan: cu_ALU2src=1, cu_immtype=001, cu_store=1, cu_storetype=10

        // SB (funct3=0)
        funct3_tb = 3'h0; #10;
        // Output diharapkan: cu_ALU2src=1, cu_immtype=001, cu_store=1, cu_storetype=00

        // --- Kasus Uji B-type (Branch) (opcode = 7'h63) ---
        $display("\n--- Uji Branch ---");
        // BEQ (funct3=0)
        opcode_tb = 7'h63; funct3_tb = 3'h0; #10;
        // Output diharapkan: cu_ALU1src=1, cu_ALU2src=1, cu_immtype=010, cu_branch=1, cu_PCtype=1, cu_branchtype=000

        // BNE (funct3=1)
        funct3_tb = 3'h1; #10;
        // Output diharapkan: cu_ALU1src=1, cu_ALU2src=1, cu_immtype=010, cu_branch=1, cu_PCtype=1, cu_branchtype=101

        // --- Kasus Uji U-type (LUI/AUIPC) ---
        $display("\n--- Uji U-type ---");
        // LUI (opcode=7'h37)
        opcode_tb = 7'h37; #10;
        // Output diharapkan: cu_ALU2src=1, cu_immtype=011, cu_rdtype=11, cu_rdwrite=1

        // AUIPC (opcode=7'h17)
        opcode_tb = 7'h17; #10;
        // Output diharapkan: cu_ALU1src=1, cu_ALU2src=1, cu_immtype=011, cu_rdwrite=1, cu_rdtype=00

        // --- Kasus Uji J-type (JAL/JALR) ---
        $display("\n--- Uji J-type ---");
        // JAL (opcode=7'h6F)
        opcode_tb = 7'h6F; #10;
        // Output diharapkan: cu_ALU1src=1, cu_ALU2src=1, cu_immtype=100, cu_rdtype=10, cu_rdwrite=1, cu_branch=1, cu_PCtype=1

        // JALR (opcode=7'h67)
        opcode_tb = 7'h67; #10;
        // Output diharapkan: cu_ALU1src=0 (default), cu_ALU2src=1, cu_immtype=000, cu_rdtype=10, cu_rdwrite=1, cu_branch=1, cu_PCtype=1

        $display("\nSimulasi Control Unit selesai.");
        $finish;
    end

endmodule

EL3011_2_20251119_13223048/1_lab/Tugas1/cu_sim.vcd
$date
	Wed Nov 19 13:39:06 2025
$end
$version
	Icarus Verilog
$end
$timescale
	1ps
$end
$scope module tb_ctrl_unit_rv32i $end
$var wire 2 ! cu_storetype_tb [1:0] $end
$var wire 1 " cu_store_tb $end
$var wire 1 # cu_sltype_tb $end
$var wire 2 $ cu_shiftype_tb [1:0] $end
$var wire 1 % cu_rdwrite_tb $end
$var wire 2 & cu_rdtype_tb [1:0] $end
$var wire 3 ' cu_loadtype_tb [2:0] $end
$var wire 3 ( cu_immtype_tb [2:0] $end
$var wire 2 ) cu_gatype_tb [1:0] $end
$var wire 3 * cu_branchtype_tb [2:0] $end
$var wire 1 + cu_branch_tb $end
$var wire 1 , cu_adtype_tb $end
$var wire 1 - cu_PCtype_tb $end
$var wire 2 . cu_ALUtype_tb [1:0] $end
$var wire 1 / cu_ALU2src_tb $end
$var wire 1 0 cu_ALU1src_tb $end
$var reg 3 1 funct3_tb [2:0] $end
$var reg 7 2 funct7_tb [6:0] $end
$var reg 7 3 opcode_tb [6:0] $end
$scope module uut $end
$var wire 3 4 funct3 [2:0] $end
$var wire 7 5 funct7 [6:0] $end
$var wire 7 6 opcode [6:0] $end
$var reg 1 0 cu_ALU1src $end
$var reg 1 / cu_ALU2src $end
$var reg 2 7 cu_ALUtype [1:0] $end
$var reg 1 - cu_PCtype $end
$var reg 1 , cu_adtype $end
$var reg 1 + cu_branch $end
$var reg 3 8 cu_branchtype [2:0] $end
$var reg 2 9 cu_gatype [1:0] $end
$var reg 3 : cu_immtype [2:0] $end
$var reg 3 ; cu_loadtype [2:0] $end
$var reg 2 < cu_rdtype [1:0] $end
$var reg 1 % cu_rdwrite $end
$var reg 2 = cu_shiftype [1:0] $end
$var reg 1 # cu_sltype $end
$var reg 1 " cu_store $end
$var reg 2 > cu_storetype [1:0] $end
$upscope $end
$upscope $end
$enddefinitions $end
$comment Show the parameter values. $end
$dumpall
$end
#0
$dumpvars
b0 >
b0 =
b0 <
b10 ;
b0 :
b0 9
b0 8
b0 7
b0 6
b0 5
b0 4
b0 3
b0 2
b0 1
00
0/
b0 .
0-
0,
0+
b0 *
b0 )
b0 (
b10 '
b0 &
0%
b0 $
0#
0"
b0 !
$end
#10000
1%
b110011 3
b110011 6
#20000
1,
1%
b100000 2
b100000 5
#30000
b10 .
b10 7
1%
0,
b0 2
b0 5
b1 1
b1 4
#40000
1#
1%
b11 .
b11 7
b11 1
b11 4
#50000
b10 )
b10 9
1%
0#
b1 .
b1 7
b100 1
b100 4
#60000
b1 $
b1 =
1%
b0 )
b0 9
b10 .
b10 7
b101 1
b101 4
#70000
1%
b11 $
b11 =
b10 .
b10 7
b100000 2
b100000 5
#80000
1/
1%
b0 $
b0 =
b0 .
b0 7
b0 2
b0 5
b0 1
b0 4
b10011 3
b10011 6
#90000
b10 )
b10 9
b1 .
b1 7
1%
1/
b100 1
b100 4
#100000
b1 &
b1 <
1%
b0 )
b0 9
b0 .
b0 7
1/
b10 1
b10 4
b11 3
b11 6
#110000
b11 '
b11 ;
1%
b1 &
b1 <
1/
b11 1
b11 4
#120000
b10 !
b10 >
1"
b1 (
b1 :
b10 '
b10 ;
0%
b0 &
b0 <
1/
b10 1
b10 4
b100011 3
b100011 6
#130000
b0 !
b0 >
1"
b1 (
b1 :
1/
b0 1
b0 4
#140000
1-
1+
10
0"
b10 (
b10 :
1/
b1100011 3
b1100011 6
#150000
b101 *
b101 8
1-
1+
b10 (
b10 :
1/
10
b1 1
b1 4
#160000
1%
b11 &
b11 <
0-
b0 *
b0 8
0+
b11 (
b11 :
1/
00
b110111 3
b110111 6
#170000
10
1%
b0 &
b0 <
b11 (
b11 :
1/
b10111 3
b10111 6
#180000
1-
1+
b10 &
b10 <
1%
b100 (
b100 :
1/
10
b1101111 3
b1101111 6
#190000
1-
1+
1%
b10 &
b10 <
b0 (
b0 :
1/
00
b1100111 3
b1100111 6
