EL3011_2_20251119_13223048/1_lab/Tugas 3/brancher_rv32i.v
// Praktikum EL3011 Arsitektur Sistem Komputer
// Modul      : 2
// Percobaan  : 3
// Tanggal    : 19 November 2025
// Nama (NIM) 1 : William Anthony (13223048)
// Nama (NIM) 2 : Agita Trinanda Ilmi (13223003)
// Nama File    : brancher_rv32i.v
// Deskripsi    : Brancher untuk RV32I 

module brancher_rv32i(
    input wire [31:0] PCnew,   // PC+4 dari 4-adder 
    input wire [31:0] ALUout,  // PC+imm dari ALU 
    input wire signed [31:0] in1, // Nilai di rs1
    input wire signed [31:0] in2, // Nilai di rs2 
    input wire cu_branch,       // Enable branch 
    input wire [2:0] cu_branchtype, // Tipe branch 
    output reg [31:0] PCin
);

    // N I L A I N Y A          DI B E R I K A N 
    // $BEQ=3'b000, $BGE=3'b001, $BGEU=3'b010, $BLT=3'b011,
    // $BLTU=3'b100, $BNE=3'b101 [cite: 379, 382-383]

    always @ (*)
    begin
        if (cu_branch) 
        begin
            case (cu_branchtype) 
                // BEQ (Branch if Equal)
                3'b000: 
                    PCin <= (in1 == in2) ? ALUout : PCnew;
                
                // BGE (Branch if Greater or Equal - Signed)
                3'b001: 
                    PCin <= (in1 >= in2) ? ALUout : PCnew; 
                
                // BGEU (Branch if Greater or Equal - Unsigned)
                3'b010: 
                    PCin <= ($unsigned(in1) >= $unsigned(in2)) ? ALUout : PCnew; 
                
                // BLT (Branch if Less Than - Signed)
                3'b011: 
                    PCin <= (in1 < in2) ? ALUout : PCnew; 
                
                // BLTU (Branch if Less Than - Unsigned)
                3'b100: 
                    PCin <= ($unsigned(in1) < $unsigned(in2)) ? ALUout : PCnew; 
                
                // BNE (Branch if Not Equal)
                3'b101: 
                    PCin <= (in1 != in2) ? ALUout : PCnew; 
                
                // Default: jika tidak ada branch, teruskan PC+4
                default: 
                    PCin <= PCnew; 
            endcase
        end
        else
        begin
            PCin <= PCnew; 
        end
    end

endmodule

EL3011_2_20251119_13223048/1_lab/Tugas3/tb_brancher_rv32i.v
// Praktikum EL3011 Arsitektur Sistem Komputer
// Modul      : 2
// Percobaan  : 3
// Tanggal    : 19 November 2025
// Nama (NIM) 1 : William Anthony (13223048)
// Nama (NIM) 2 : Agita Trinanda Ilmi (13223003)
// Nama File  : tb_brancher_rv32i.v
// Deskripsi  : Testbench untuk Brancher RV32I

`timescale 1ns / 1ps

module tb_brancher_rv32i;

    // Deklarasi sinyal testbench untuk input Brancher
    reg  [31:0] pc_new_tb;   // PC+4 dari 4-adder (input ke Brancher)
    reg  [31:0] alu_out_tb;  // PC+imm dari ALU (target branch/jump)
    reg signed [31:0] in1_tb;    // Nilai register rs1
    reg signed [31:0] in2_tb;    // Nilai register rs2
    reg        cu_branch_tb;       // Enable branch dari CU
    reg  [2:0]  cu_branchtype_tb; // Tipe branch dari CU

    // Deklarasi sinyal testbench untuk output Brancher
    wire [31:0] pcin_tb; // PCin (alamat PC selanjutnya)

    // Instansiasi Unit Under Test (UUT)
    // Diasumsikan brancher_rv32i.v ada di direktori yang sama
    brancher_rv32i uut (
        .PCnew(pc_new_tb),
        .ALUout(alu_out_tb),
        .in1(in1_tb),
        .in2(in2_tb),
        .cu_branch(cu_branch_tb),
        .cu_branchtype(cu_branchtype_tb),
        .PCin(pcin_tb)
    );

    initial begin
        // Konfigurasi pencatatan waveform
        $dumpfile("brancher_sim.vcd");
        $dumpvars(0, tb_brancher_rv32i);

        // --- Inisialisasi ---
        pc_new_tb = 32'h00000004;
        alu_out_tb = 32'h00001000;
        in1_tb = 0; in2_tb = 0;
        cu_branch_tb = 0; cu_branchtype_tb = 3'b000; // Default: no branch, PCin = PCnew
        #10;
        // Output pcin_tb diharapkan: 0x00000004

        // --- Kasus Uji BEQ (Branch if Equal) ---
        $display("\n--- Uji BEQ ---");
        pc_new_tb = 32'h00000008; // PC+4 jika tidak branch
        alu_out_tb = 32'h00001100; // Target branch jika kondisi true
        in1_tb = 10; in2_tb = 10; // Kondisi true (in1 == in2)
        cu_branch_tb = 1; cu_branchtype_tb = 3'b000; // BEQ
        #10;
        // Output pcin_tb diharapkan: 0x00001100 (melompat)

        // Kasus BEQ (False)
        in1_tb = 10; in2_tb = 11; // Kondisi false (in1 != in2)
        #10;
        // Output pcin_tb diharapkan: 0x00000008 (tidak melompat, gunakan PCnew)

        // --- Kasus Uji BNE (Branch if Not Equal) ---
        $display("\n--- Uji BNE ---");
        pc_new_tb = 32'h00000012;
        alu_out_tb = 32'h00001200;
        in1_tb = 5; in2_tb = 10; // Kondisi true (in1 != in2)
        cu_branch_tb = 1; cu_branchtype_tb = 3'b101; // BNE
        #10;
        // Output pcin_tb diharapkan: 0x00001200 (melompat)

        // Kasus BNE (False)
        in1_tb = 10; in2_tb = 10; // Kondisi false (in1 == in2)
        #10;
        // Output pcin_tb diharapkan: 0x00000012 (tidak melompat, gunakan PCnew)

        // --- Kasus Uji BLT (Branch if Less Than - Signed) ---
        $display("\n--- Uji BLT ---");
        pc_new_tb = 32'h00000016;
        alu_out_tb = 32'h00001300;
        in1_tb = -5; in2_tb = 0; // Kondisi true (-5 < 0)
        cu_branch_tb = 1; cu_branchtype_tb = 3'b011; // BLT
        #10;
        // Output pcin_tb diharapkan: 0x00001300 (melompat)

        // Kasus BLT (False)
        in1_tb = 5; in2_tb = 0; // Kondisi false (5 < 0 salah)
        #10;
        // Output pcin_tb diharapkan: 0x00000016 (tidak melompat)
        
        // --- Kasus Uji BGE (Branch if Greater or Equal - Signed) ---
        $display("\n--- Uji BGE ---");
        pc_new_tb = 32'h00000020;
        alu_out_tb = 32'h00001400;
        in1_tb = 10; in2_tb = 5; // Kondisi true (10 >= 5)
        cu_branch_tb = 1; cu_branchtype_tb = 3'b001; // BGE
        #10;
        // Output pcin_tb diharapkan: 0x00001400 (melompat)

        // Kasus BGE (False)
        in1_tb = 0; in2_tb = 5; // Kondisi false (0 >= 5 salah)
        #10;
        // Output pcin_tb diharapkan: 0x00000020 (tidak melompat)

        // --- Kasus Uji BLTU (Branch if Less Than - Unsigned) ---
        $display("\n--- Uji BLTU ---");
        pc_new_tb = 32'h00000024;
        alu_out_tb = 32'h00001500;
        in1_tb = 32'h0000000A; // 10 (unsigned)
        in2_tb = 32'h00000014; // 20 (unsigned)
        // (10 < 20) true
        cu_branch_tb = 1; cu_branchtype_tb = 3'b100; // BLTU
        #10;
        // Output pcin_tb diharapkan: 0x00001500 (melompat)

        // Kasus BLTU (False - perbandingan unsigned)
        in1_tb = 32'hFFFFFFFF; // -1 (signed) -> 4294967295 (unsigned)
        in2_tb = 32'h0000000A; // 10 (unsigned)
        // (4294967295 < 10) false
        #10;
        // Output pcin_tb diharapkan: 0x00000024 (tidak melompat)


        // --- Kasus Uji BGEU (Branch if Greater or Equal - Unsigned) ---
        $display("\n--- Uji BGEU ---");
        pc_new_tb = 32'h00000028;
        alu_out_tb = 32'h00001600;
        in1_tb = 32'hFFFFFFF0; // -16 (signed) -> 4294967280 (unsigned)
        in2_tb = 32'h00000064; // 100 (unsigned)
        // (4294967280 >= 100) true
        cu_branch_tb = 1; cu_branchtype_tb = 3'b010; // BGEU
        #10;
        // Output pcin_tb diharapkan: 0x00001600 (melompat)

        // Kasus BGEU (False)
        in1_tb = 32'h00000005; // 5 (unsigned)
        in2_tb = 32'h0000000A; // 10 (unsigned)
        // (5 >= 10) false
        #10;
        // Output pcin_tb diharapkan: 0x00000028 (tidak melompat)

        // --- Non-branching (cu_branch = 0) ---
        $display("\n--- Uji Non-branching ---");
        pc_new_tb = 32'h00000030;
        cu_branch_tb = 0; // Pastikan tidak ada branch, PCin harus selalu PCnew
        #10;
        // Output pcin_tb diharapkan: 0x00000030

        $display("\nSimulasi Brancher selesai.");
        $finish;
    end

endmodule

EL3011_2_20251119_13223048/1_lab/Tugas3/brancher_sim.vcd
$date
	Wed Nov 19 13:45:07 2025
$end
$version
	Icarus Verilog
$end
$timescale
	1ps
$end
$scope module tb_brancher_rv32i $end
$var wire 32 ! pcin_tb [31:0] $end
$var reg 32 " alu_out_tb [31:0] $end
$var reg 1 # cu_branch_tb $end
$var reg 3 $ cu_branchtype_tb [2:0] $end
$var reg 32 % in1_tb [31:0] $end
$var reg 32 & in2_tb [31:0] $end
$var reg 32 ' pc_new_tb [31:0] $end
$scope module uut $end
$var wire 32 ( ALUout [31:0] $end
$var wire 32 ) PCnew [31:0] $end
$var wire 1 # cu_branch $end
$var wire 3 * cu_branchtype [2:0] $end
$var wire 32 + in1 [31:0] $end
$var wire 32 , in2 [31:0] $end
$var reg 32 - PCin [31:0] $end
$upscope $end
$upscope $end
$enddefinitions $end
$comment Show the parameter values. $end
$dumpall
$end
#0
$dumpvars
b100 -
b0 ,
b0 +
b0 *
b100 )
b1000000000000 (
b100 '
b0 &
b0 %
b0 $
0#
b1000000000000 "
b100 !
$end
#10000
b1000100000000 !
b1000100000000 -
1#
b1010 &
b1010 ,
b1010 %
b1010 +
b1000100000000 "
b1000100000000 (
b1000 '
b1000 )
#20000
b1000 !
b1000 -
b1011 &
b1011 ,
#30000
b1001000000000 !
b1001000000000 -
b101 $
b101 *
b1010 &
b1010 ,
b101 %
b101 +
b1001000000000 "
b1001000000000 (
b10010 '
b10010 )
#40000
b10010 !
b10010 -
b1010 %
b1010 +
#50000
b1001100000000 !
b1001100000000 -
b11 $
b11 *
b0 &
b0 ,
b11111111111111111111111111111011 %
b11111111111111111111111111111011 +
b1001100000000 "
b1001100000000 (
b10110 '
b10110 )
#60000
b10110 !
b10110 -
b101 %
b101 +
#70000
b1010000000000 !
b1010000000000 -
b1 $
b1 *
b101 &
b101 ,
b1010 %
b1010 +
b1010000000000 "
b1010000000000 (
b100000 '
b100000 )
#80000
b100000 !
b100000 -
b0 %
b0 +
#90000
b1010100000000 !
b1010100000000 -
b100 $
b100 *
b10100 &
b10100 ,
b1010 %
b1010 +
b1010100000000 "
b1010100000000 (
b100100 '
b100100 )
#100000
b100100 !
b100100 -
b1010 &
b1010 ,
b11111111111111111111111111111111 %
b11111111111111111111111111111111 +
#110000
b1011000000000 !
b1011000000000 -
b10 $
b10 *
b1100100 &
b1100100 ,
b11111111111111111111111111110000 %
b11111111111111111111111111110000 +
b1011000000000 "
b1011000000000 (
b101000 '
b101000 )
#120000
b101000 !
b101000 -
b1010 &
b1010 ,
b101 %
b101 +
#130000
b110000 !
b110000 -
0#
b110000 '
b110000 )
