EL3011_2_20251119_13223048/0_prelab/Tugas3/pc_rv32i.v
// Praktikum EL3011 Arsitektur Sistem Komputer
// Modul      : 2
// Percobaan  : 3
// Tanggal    : 19 November 2025
// Nama (NIM) 1 : William Anthony (13223048)
// Nama (NIM) 2 : Agita Trinanda Ilmi (13223003)
// Nama File  : pc_rv32i.v
// Deskripsi  : Desain Program Counter (PC) 32-bit untuk RV32I

module pc_rv32i (
    input  wire        clk,      // Sinyal clock
    input  wire        reset,    // Sinyal reset (asinkron aktif-tinggi)
    input  wire [31:0] next_pc,  // Alamat PC selanjutnya
    output reg  [31:0] pc        // Output Program Counter
);

    always @(posedge clk or posedge reset) begin
        if (reset) begin
            pc <= 32'h0;      // Reset PC ke 0
        end else begin
            pc <= next_pc;    // Perbarui PC pada tepi naik clock
        end
    end

endmodule

EL3011_2_20251119_13223048/0_prelab/Tugas3/tb_pc_rv32i.v
// Praktikum EL3011 Arsitektur Sistem Komputer
// Modul      : 2
// Percobaan  : 3
// Tanggal    : 19 November 2025
// Nama (NIM) 1 : William Anthony (13223048)
// Nama (NIM) 2 : Agita Trinanda Ilmi (13223003)
// Nama File  : tb_pc_rv32i.v
// Deskripsi  : Testbench untuk Program Counter 32-bit

`timescale 1ns / 1ps

module tb_pc_rv32i;

    // Deklarasi sinyal testbench
    reg        clk_tb;
    reg        reset_tb;
    reg [31:0] next_pc_tb;
    wire [31:0] pc_tb;

    // Instansiasi Unit Under Test (UUT)
    pc_rv32i uut (
        .clk(clk_tb),
        .reset(reset_tb),
        .next_pc(next_pc_tb),
        .pc(pc_tb)
    );

    // Generasi clock
    initial begin
        clk_tb = 0;
        forever #5 clk_tb = ~clk_tb; // Perioda clock 10ns
    end

    initial begin
        // Konfigurasi pencatatan waveform
        $dumpfile("pc_sim.vcd");
        $dumpvars(0, tb_pc_rv32i);

        // Inisialisasi: aktifkan reset
        reset_tb   = 1;
        next_pc_tb = 32'h1000; #10; // PC harus 0 karena reset

        // Nonaktifkan reset, amati pembaruan PC
        reset_tb   = 0;
        #10; // PC akan jadi 0, lalu pada posedge clk berikutnya jadi 0x1000
        next_pc_tb = 32'h1004; #10; // Harapannya: PC = 0x1004
        next_pc_tb = 32'h1008; #10; // Harapannya: PC = 0x1008

        // Skenario lompat/cabang
        next_pc_tb = 32'hC000; #10; // Harapannya: PC = 0xC000
        next_pc_tb = 32'hC004; #10; // Harapannya: PC = 0xC004

        // Aktifkan reset kembali
        reset_tb   = 1; #10; // Harapannya: PC = 0

        $display("Simulasi Program Counter selesai.");
        $finish;
    end

endmodule

EL3011_2_20251119_13223048/0_prelab/Tugas3/pc_sim.vcd
$date
	Tue Nov 18 12:22:58 2025
$end
$version
	Icarus Verilog
$end
$timescale
	1ps
$end
$scope module tb_pc_rv32i $end
$var wire 32 ! pc_tb [31:0] $end
$var reg 1 " clk_tb $end
$var reg 32 # next_pc_tb [31:0] $end
$var reg 1 $ reset_tb $end
$scope module uut $end
$var wire 1 " clk $end
$var wire 32 % next_pc [31:0] $end
$var wire 1 $ reset $end
$var reg 32 & pc [31:0] $end
$upscope $end
$upscope $end
$enddefinitions $end
$comment Show the parameter values. $end
$dumpall
$end
#0
$dumpvars
b0 &
b1000000000000 %
1$
b1000000000000 #
0"
b0 !
$end
#5000
1"
#10000
0"
0$
#15000
b1000000000000 !
b1000000000000 &
1"
#20000
0"
b1000000000100 #
b1000000000100 %
#25000
b1000000000100 !
b1000000000100 &
1"
#30000
0"
b1000000001000 #
b1000000001000 %
#35000
b1000000001000 !
b1000000001000 &
1"
#40000
0"
b1100000000000000 #
b1100000000000000 %
#45000
b1100000000000000 !
b1100000000000000 &
1"
#50000
0"
b1100000000000100 #
b1100000000000100 %
#55000
b1100000000000100 !
b1100000000000100 &
1"
#60000
b0 !
b0 &
0"
1$
