EL3011_1_20251105_13223048/1_lab/Tugas1/instr_rom_rv32i.v
// ============================================================================
// Praktikum EL3011 Arsitektur Sistem Komputer
// Modul        : 1
// Percobaan    : 1
// Tanggal      : 5 November 2025
// Kelompok     : 
// Rombongan    : Rabu
// Nama (NIM) 1 : William Anthony (13223048)
// Nama (NIM) 2 : Darren Johan (13223032)
// Nama File    : instr_rom_rv32i.v
// Deskripsi    : Instruction ROM RV32I, 32x32, baca sinkron @posedge clock
// ============================================================================


module instr_rom_rv32i ( 
    input  wire [31:0] ADDR,   // byte address dari PC 
    input  wire        clock, 
    input  wire        reset, 
    output reg  [31:0] INSTR   // instruksi 32-bit 
); 
  // 32 word x 32-bit 
  reg [31:0] mem [0:31]; 
  // Word index = PC[6:2] (bit [1:0] = 2'b00) 
  wire [4:0] waddr = ADDR[6:2]; 
 
  integer i; 
  initial begin 
    // Default: semua NOP (addi x0,x0,0) 
    for (i = 0; i < 32; i = i + 1) mem[i] = 32'h00000013; 
 
    // Isi program (ganti sesuai dengan "Machine Code" dari Venus pada Tugas Pendahuluan nomor 3!): 
    mem[0] = 32'h00500093; // addi x1,x0,5 
    mem[1] = 32'h00700113; // addi x2,x0,7 
    mem[2] = 32'h002081B3; // add  x3,x1,x2 
    mem[3] = 32'h00302023; // sw   x3,0(x0) 
    
    // Alternatif: load dari file heksa 
    //$readmemh("imemory_rv32i.hex", mem); 
  end 
 
  // Baca sinkron; reset keluarkan NOP 
  always @(posedge clock or posedge reset) begin 
    if (reset) INSTR <= 32'h00000013;   // NOP RV32I 
    else       INSTR <= mem[waddr]; 
  end 
endmodule

EL3011_1_20251105_13223048/Tugas1/instr_rom_rv32i_tb.v
// ============================================================================
// Praktikum EL3011 Arsitektur Sistem Komputer
// Modul        : 1
// Percobaan    : 1
// Tanggal      : 5 November 2025
// Kelompok     : 
// Rombongan    : Rabu
// Nama (NIM) 1 : William Anthony (13223048)
// Nama (NIM) 2 : Darren Johan (13223032)
// Nama File    : instr_rom_rv32i_tb.v
// Deskripsi    : Testbench untuk menguji modul instr_rom_rv32i (Instruction ROM RV32I)
// Lokasi File  : D:\ARSIKOM\EL3011_1_20251105_13223048\Tugas1
// ============================================================================

`timescale 1ns/1ps

module instr_rom_rv32i_tb;

  // --------------------------------------------------------------------------
  // Deklarasi sinyal untuk menghubungkan testbench dengan DUT (Device Under Test)
  // --------------------------------------------------------------------------
  reg  [31:0] ADDR;   // alamat byte (input)
  reg         clock;  // sinyal clock
  reg         reset;  // sinyal reset
  wire [31:0] INSTR;  // instruksi keluaran (output)

  // --------------------------------------------------------------------------
  // Instansiasi modul yang diuji (instr_rom_rv32i)
  // --------------------------------------------------------------------------
  instr_rom_rv32i dut (
    .ADDR(ADDR),
    .clock(clock),
    .reset(reset),
    .INSTR(INSTR)
  );

  // --------------------------------------------------------------------------
  // Parameter dan variabel bantu
  // --------------------------------------------------------------------------
  localparam NOP        = 32'h00000013;   // Instruksi NOP RV32I (addi x0,x0,0)
  localparam CLK_PERIOD = 10;             // Periode clock 10 ns (100 MHz)
  integer i;

  // Array untuk nilai instruksi yang diharapkan
  reg [31:0] expected [0:31];

  // --------------------------------------------------------------------------
  // Inisialisasi nilai ekspektasi (harus sama dengan isi mem di modul utama)
  // --------------------------------------------------------------------------
  initial begin
    // Semua alamat berisi NOP secara default
    for (i = 0; i < 32; i = i + 1)
      expected[i] = NOP;

    // Isi instruksi sesuai dengan program contoh pada modul
    expected[0] = 32'h00500093; // addi x1,x0,5
    expected[1] = 32'h00700113; // addi x2,x0,7
    expected[2] = 32'h002081B3; // add  x3,x1,x2
    expected[3] = 32'h00302023; // sw   x3,0(x0)
  end

  // --------------------------------------------------------------------------
  // Pembangkit clock periodik
  // --------------------------------------------------------------------------
  initial begin
    clock = 0;
    forever #(CLK_PERIOD/2) clock = ~clock;
  end

  // --------------------------------------------------------------------------
  // Simpan data simulasi ke file VCD agar bisa dilihat di GTKWave
  // --------------------------------------------------------------------------
  initial begin
    $dumpfile("instr_rom_rv32i_tb.vcd");
    $dumpvars(0, instr_rom_rv32i_tb);
  end

  // --------------------------------------------------------------------------
  // Proses pengujian utama
  // --------------------------------------------------------------------------
  initial begin
    // Tahap 1: Reset awal
    ADDR  = 32'd0;
    reset = 1'b1;

    // Tunggu dua siklus clock untuk memastikan reset bekerja
    repeat (2) @(posedge clock);
    if (INSTR !== NOP)
      $display("GAGAL: Saat reset, INSTR = %h (seharusnya NOP = %h)", INSTR, NOP);
    else
      $display("OK: Saat reset, INSTR = NOP (%h)", INSTR);

    // Tahap 2: Lepaskan reset
    @(posedge clock);
    reset = 1'b0;

    // Tahap 3: Uji pembacaan setiap alamat word-aligned (0,4,8,...,124)
    for (i = 0; i < 32; i = i + 1) begin
      ADDR = i * 4;           // byte address
      @(posedge clock); #1;   // tunggu perubahan output
      if (INSTR !== expected[i])
        $display("GAGAL: addr=%0d (byte %0d) -> INSTR=%h, seharusnya=%h", i, i*4, INSTR, expected[i]);
      else
        $display("BERHASIL: addr=%0d (byte %0d) -> INSTR=%h", i, i*4, INSTR);
    end

    // Tahap 4: Uji alamat tidak sejajar word (misal ADDR = 1 dan 5)
    ADDR = 32'd1;
    @(posedge clock); #1;
    if (INSTR !== expected[0])
      $display("GAGAL: Alamat 1 tidak memetakan ke word 0. INSTR=%h", INSTR);
    else
      $display("OK: Alamat 1 memetakan ke word 0 -> INSTR=%h", INSTR);

    ADDR = 32'd5;
    @(posedge clock); #1;
    if (INSTR !== expected[1])
      $display("GAGAL: Alamat 5 tidak memetakan ke word 1. INSTR=%h", INSTR);
    else
      $display("OK: Alamat 5 memetakan ke word 1 -> INSTR=%h", INSTR);

    // Tahap 5: Uji ulang reset di akhir
    reset = 1'b1;
    @(posedge clock); #1;
    if (INSTR !== NOP)
      $display("GAGAL: Setelah reset ulang, INSTR=%h (seharusnya NOP=%h)", INSTR, NOP);
    else
      $display("OK: Setelah reset ulang, INSTR = NOP (%h)", INSTR);

    reset = 1'b0;
    @(posedge clock);

    $display("SEMUA PENGUJIAN SELESAI TANPA ERROR.");
    $finish;
  end

endmodule

 /*
 cd D:\ARSIKOM\EL3011_1_20251105_13223048\Tugas1
 iverilog -o instr_rom_tb.vvp instr_rom_rv32i.v instr_rom_rv32i_tb.v
 vvp instr_rom_tb.vvp
 gtkwave instr_rom_rv32i_tb.vcd
 */

EL3011_1_20251105_13223048/1_lab/Tugas1/instr_rom_rv32i_tb.vcd
$date
	Tue Nov 04 19:23:12 2025
$end
$version
	Icarus Verilog
$end
$timescale
	1ps
$end
$scope module instr_rom_rv32i_tb $end
$var wire 32 ! INSTR [31:0] $end
$var parameter 32 " CLK_PERIOD $end
$var parameter 32 # NOP $end
$var reg 32 $ ADDR [31:0] $end
$var reg 1 % clock $end
$var reg 1 & reset $end
$var integer 32 ' i [31:0] $end
$scope module dut $end
$var wire 32 ( ADDR [31:0] $end
$var wire 1 % clock $end
$var wire 1 & reset $end
$var wire 5 ) waddr [4:0] $end
$var reg 32 * INSTR [31:0] $end
$var integer 32 + i [31:0] $end
$upscope $end
$upscope $end
$enddefinitions $end
$comment Show the parameter values. $end
$dumpall
b10011 #
b1010 "
$end
#0
$dumpvars
b100000 +
b10011 *
b0 )
b0 (
b100000 '
1&
0%
b0 $
b10011 !
$end
#5000
1%
#10000
0%
#15000
1%
#20000
0%
#25000
b10100000000000010010011 !
b10100000000000010010011 *
b0 '
0&
1%
#30000
0%
#35000
1%
#36000
b1 )
b100 $
b100 (
b1 '
#40000
0%
#45000
b11100000000000100010011 !
b11100000000000100010011 *
1%
#46000
b10 )
b1000 $
b1000 (
b10 '
#50000
0%
#55000
b1000001000000110110011 !
b1000001000000110110011 *
1%
#56000
b11 )
b1100 $
b1100 (
b11 '
#60000
0%
#65000
b1100000010000000100011 !
b1100000010000000100011 *
1%
#66000
b100 )
b10000 $
b10000 (
b100 '
#70000
0%
#75000
b10011 !
b10011 *
1%
#76000
b101 )
b10100 $
b10100 (
b101 '
#80000
0%
#85000
1%
#86000
b110 )
b11000 $
b11000 (
b110 '
#90000
0%
#95000
1%
#96000
b111 )
b11100 $
b11100 (
b111 '
#100000
0%
#105000
1%
#106000
b1000 )
b100000 $
b100000 (
b1000 '
#110000
0%
#115000
1%
#116000
b1001 )
b100100 $
b100100 (
b1001 '
#120000
0%
#125000
1%
#126000
b1010 )
b101000 $
b101000 (
b1010 '
#130000
0%
#135000
1%
#136000
b1011 )
b101100 $
b101100 (
b1011 '
#140000
0%
#145000
1%
#146000
b1100 )
b110000 $
b110000 (
b1100 '
#150000
0%
#155000
1%
#156000
b1101 )
b110100 $
b110100 (
b1101 '
#160000
0%
#165000
1%
#166000
b1110 )
b111000 $
b111000 (
b1110 '
#170000
0%
#175000
1%
#176000
b1111 )
b111100 $
b111100 (
b1111 '
#180000
0%
#185000
1%
#186000
b10000 )
b1000000 $
b1000000 (
b10000 '
#190000
0%
#195000
1%
#196000
b10001 )
b1000100 $
b1000100 (
b10001 '
#200000
0%
#205000
1%
#206000
b10010 )
b1001000 $
b1001000 (
b10010 '
#210000
0%
#215000
1%
#216000
b10011 )
b1001100 $
b1001100 (
b10011 '
#220000
0%
#225000
1%
#226000
b10100 )
b1010000 $
b1010000 (
b10100 '
#230000
0%
#235000
1%
#236000
b10101 )
b1010100 $
b1010100 (
b10101 '
#240000
0%
#245000
1%
#246000
b10110 )
b1011000 $
b1011000 (
b10110 '
#250000
0%
#255000
1%
#256000
b10111 )
b1011100 $
b1011100 (
b10111 '
#260000
0%
#265000
1%
#266000
b11000 )
b1100000 $
b1100000 (
b11000 '
#270000
0%
#275000
1%
#276000
b11001 )
b1100100 $
b1100100 (
b11001 '
#280000
0%
#285000
1%
#286000
b11010 )
b1101000 $
b1101000 (
b11010 '
#290000
0%
#295000
1%
#296000
b11011 )
b1101100 $
b1101100 (
b11011 '
#300000
0%
#305000
1%
#306000
b11100 )
b1110000 $
b1110000 (
b11100 '
#310000
0%
#315000
1%
#316000
b11101 )
b1110100 $
b1110100 (
b11101 '
#320000
0%
#325000
1%
#326000
b11110 )
b1111000 $
b1111000 (
b11110 '
#330000
0%
#335000
1%
#336000
b11111 )
b1111100 $
b1111100 (
b11111 '
#340000
0%
#345000
1%
#346000
b0 )
b1 $
b1 (
b100000 '
#350000
0%
#355000
b10100000000000010010011 !
b10100000000000010010011 *
1%
#356000
b1 )
b101 $
b101 (
#360000
0%
#365000
b11100000000000100010011 !
b11100000000000100010011 *
1%
#366000
b10011 !
b10011 *
1&
#370000
0%
#375000
1%
#376000
0&
#380000
0%
#385000
b11100000000000100010011 !
b11100000000000100010011 *
1%
